forwhat/__init__.py
forwhat/__main__.py
forwhat/a/A.py
forwhat/a/__init__.py
forwhat-0.1.1.dist-info/LICENSE
forwhat-0.1.1.dist-info/METADATA
forwhat-0.1.1.dist-info/WHEEL
forwhat-0.1.1.dist-info/RECORD
